asynciobase/__init__.py
asynciobase-0.2.0.dist-info/WHEEL
asynciobase-0.2.0.dist-info/METADATA
asynciobase-0.2.0.dist-info/RECORD
